zabbixasync/__init__.py
zabbixasync/sender.py
zabbix_sender_async-1.0.4.dist-info/METADATA
zabbix_sender_async-1.0.4.dist-info/WHEEL
zabbix_sender_async-1.0.4.dist-info/licenses/LICENSE
zabbix_sender_async-1.0.4.dist-info/RECORD
