Metadata-Version: 2.1
Name: zabbix-sender-async
Version: 1.0.4
Summary: A Zabbix sender module with async features
Project-URL: Homepage, https://github.com/gustavofbreunig/zabbix-sender-async
Project-URL: Issues, https://github.com/gustavofbreunig/zabbix-sender-async/issues
Author-email: Gustavo Breunig <gustavofbreunig@gmail.com>
License:                     GNU GENERAL PUBLIC LICENSE
License-File: LICENSE
Keywords: async,sender,zabbix
Classifier: License :: OSI Approved :: GNU General Public License v3 (GPLv3)
Classifier: Operating System :: OS Independent
Classifier: Programming Language :: Python :: 3
Classifier: Topic :: System :: Monitoring
Classifier: Topic :: System :: Networking :: Monitoring
Classifier: Topic :: System :: Systems Administration
Requires-Python: >=3.8
Requires-Dist: python-dotenv
